appxf/__init__.py
appxf/fileversions.py
appxf/logging.py
appxf-0.0.2.dist-info/METADATA
appxf-0.0.2.dist-info/WHEEL
appxf-0.0.2.dist-info/licenses/LICENSE
appxf-0.0.2.dist-info/RECORD
