Metadata-Version: 2.3
Name: appxf
Version: 0.0.2
Summary: APPXF assists python applications (APP) by delivering the cross functional (XF) concerns 
Author-email: alexander-rd <mail@alexander-rd.de>
License-File: LICENSE
Classifier: Programming Language :: Python :: 3
Requires-Python: >=3.10
